qnq/__init__.py
qnq/qnq.py
qnq/operators/__init__.py
qnq/operators/qnq_ops/__init__.py
qnq/operators/qnq_ops/input.py
qnq/operators/qnq_ops/rnn.py
qnq/operators/qnq_ops/torchfunc.py
qnq/operators/qnq_ops/yolo.py
qnq/operators/quant_ops/__init__.py
qnq/operators/quant_ops/activation.py
qnq/operators/quant_ops/complex.py
qnq/operators/quant_ops/convolution.py
qnq/operators/quant_ops/dropout.py
qnq/operators/quant_ops/linear.py
qnq/operators/quant_ops/normalization.py
qnq/operators/quant_ops/padding.py
qnq/operators/quant_ops/pooling.py
qnq/operators/quant_ops/quant_base.py
qnq/operators/quant_ops/recurrent.py
qnq/operators/quant_ops/sparse.py
qnq/operators/quant_ops/torchfunc.py
qnq/operators/quant_ops/transformer.py
qnq/operators/quant_ops/vision.py
qnq/utils/__init__.py
qnq/utils/decorators.py
qnq/utils/onnx.py
qnq/utils/quant_utils.py
qnq-1.1.2.dist-info/LICENSE
qnq-1.1.2.dist-info/METADATA
qnq-1.1.2.dist-info/WHEEL
qnq-1.1.2.dist-info/top_level.txt
qnq-1.1.2.dist-info/RECORD
