Metadata-Version: 2.1
Name: qnq
Version: 1.1.2
Summary: qnq's not quantization
Home-page: https://pypi.org/project/qnq/
Author: Zhiwei Dong
Author-email: dongz.cn@outlook.com
License: MIT
Platform: UNKNOWN
Classifier: License :: OSI Approved :: MIT License
Classifier: Programming Language :: Python
Classifier: Programming Language :: Python :: 3
Classifier: Programming Language :: Python :: 3.6
Classifier: Programming Language :: Python :: Implementation :: CPython
Classifier: Programming Language :: Python :: Implementation :: PyPy
Requires-Python: >=3.6.0
License-File: LICENSE
Requires-Dist: numpy
Requires-Dist: torch (>=1.3)
Requires-Dist: tensorboard
Requires-Dist: pyyaml
